{
  "collectionName": "components_v1_why_choose_us_components",
  "info": {
    "displayName": "whyChooseUsComponent"
  },
  "options": {},
  "attributes": {
    "TagLine": {
      "type": "string"
    },
    "mainTitle": {
      "type": "string"
    },
    "mainDescription": {
      "type": "text"
    },
    "ButtonText": {
      "type": "string"
    },
    "headingDescription": {
      "type": "component",
      "component": "v1.title-description-component",
      "repeatable": true
    }
  },
  "config": {}
}
